<?xml version="1.0" ?>
<!--
/**
 * @package Goomento_PageBuilder
 * @link https://github.com/Goomento/PageBuilder
 */
-->
<widgets xmlns:xsi="http://www.w3.org/2001/XMLSchema-instance" xsi:noNamespaceSchemaLocation="urn:magento:helloworld:Magento_Widget:etc/widget.xsd">
    <widget class="PageBuilderRenderer" id="pagebuilder.content">
        <label>Page Builder Content</label>
        <description>Page Builder Content Renderer</description>
        <parameters>
            <parameter name="identifier" xsi:type="select" required="true" visible="true"
                       source_model="Goomento\PageBuilder\Model\Config\Source\PageList">
                <label translate="true">Page or Section</label>
            </parameter>
        </parameters>
    </widget>
</widgets>
